{"nodes": [{"id": "c_users_salivs_data_laragon_www_sigapp_dev_app_libraries_refactor_exceptions_securityexception_php", "label": "SecurityException.php", "file_type": "code", "source_file": "C:\\Users\\Salivs\\Data\\laragon\\www\\sigapp.dev\\app\\Libraries\\Refactor\\Exceptions\\SecurityException.php", "source_location": "L1"}, {"id": "exceptions_securityexception_securityexception", "label": "SecurityException", "file_type": "code", "source_file": "C:\\Users\\Salivs\\Data\\laragon\\www\\sigapp.dev\\app\\Libraries\\Refactor\\Exceptions\\SecurityException.php", "source_location": "L13"}, {"id": "exceptions_securityexception_securityexception_construct", "label": ".__construct()", "file_type": "code", "source_file": "C:\\Users\\Salivs\\Data\\laragon\\www\\sigapp.dev\\app\\Libraries\\Refactor\\Exceptions\\SecurityException.php", "source_location": "L30"}, {"id": "exceptions_securityexception_securityexception_ruleloadfailed", "label": ".ruleLoadFailed()", "file_type": "code", "source_file": "C:\\Users\\Salivs\\Data\\laragon\\www\\sigapp.dev\\app\\Libraries\\Refactor\\Exceptions\\SecurityException.php", "source_location": "L46"}, {"id": "exceptions_securityexception_securityexception_patterninvalid", "label": ".patternInvalid()", "file_type": "code", "source_file": "C:\\Users\\Salivs\\Data\\laragon\\www\\sigapp.dev\\app\\Libraries\\Refactor\\Exceptions\\SecurityException.php", "source_location": "L67"}, {"id": "exceptions_securityexception_securityexception_scanfailed", "label": ".scanFailed()", "file_type": "code", "source_file": "C:\\Users\\Salivs\\Data\\laragon\\www\\sigapp.dev\\app\\Libraries\\Refactor\\Exceptions\\SecurityException.php", "source_location": "L88"}], "edges": [{"source": "c_users_salivs_data_laragon_www_sigapp_dev_app_libraries_refactor_exceptions_securityexception_php", "target": "exceptions_securityexception_securityexception", "relation": "contains", "confidence": "EXTRACTED", "source_file": "C:\\Users\\Salivs\\Data\\laragon\\www\\sigapp.dev\\app\\Libraries\\Refactor\\Exceptions\\SecurityException.php", "source_location": "L13", "weight": 1.0}, {"source": "exceptions_securityexception_securityexception", "target": "exceptions_securityexception_securityexception_construct", "relation": "method", "confidence": "EXTRACTED", "source_file": "C:\\Users\\Salivs\\Data\\laragon\\www\\sigapp.dev\\app\\Libraries\\Refactor\\Exceptions\\SecurityException.php", "source_location": "L30", "weight": 1.0}, {"source": "exceptions_securityexception_securityexception", "target": "exceptions_securityexception_securityexception_ruleloadfailed", "relation": "method", "confidence": "EXTRACTED", "source_file": "C:\\Users\\Salivs\\Data\\laragon\\www\\sigapp.dev\\app\\Libraries\\Refactor\\Exceptions\\SecurityException.php", "source_location": "L46", "weight": 1.0}, {"source": "exceptions_securityexception_securityexception", "target": "exceptions_securityexception_securityexception_patterninvalid", "relation": "method", "confidence": "EXTRACTED", "source_file": "C:\\Users\\Salivs\\Data\\laragon\\www\\sigapp.dev\\app\\Libraries\\Refactor\\Exceptions\\SecurityException.php", "source_location": "L67", "weight": 1.0}, {"source": "exceptions_securityexception_securityexception", "target": "exceptions_securityexception_securityexception_scanfailed", "relation": "method", "confidence": "EXTRACTED", "source_file": "C:\\Users\\Salivs\\Data\\laragon\\www\\sigapp.dev\\app\\Libraries\\Refactor\\Exceptions\\SecurityException.php", "source_location": "L88", "weight": 1.0}], "raw_calls": [{"caller_nid": "exceptions_securityexception_securityexception_construct", "callee": "parent", "is_member_call": false, "source_file": "C:\\Users\\Salivs\\Data\\laragon\\www\\sigapp.dev\\app\\Libraries\\Refactor\\Exceptions\\SecurityException.php", "source_location": "L36"}, {"caller_nid": "exceptions_securityexception_securityexception_ruleloadfailed", "callee": "setContext", "is_member_call": true, "source_file": "C:\\Users\\Salivs\\Data\\laragon\\www\\sigapp.dev\\app\\Libraries\\Refactor\\Exceptions\\SecurityException.php", "source_location": "L53"}, {"caller_nid": "exceptions_securityexception_securityexception_patterninvalid", "callee": "setContext", "is_member_call": true, "source_file": "C:\\Users\\Salivs\\Data\\laragon\\www\\sigapp.dev\\app\\Libraries\\Refactor\\Exceptions\\SecurityException.php", "source_location": "L74"}, {"caller_nid": "exceptions_securityexception_securityexception_scanfailed", "callee": "setContext", "is_member_call": true, "source_file": "C:\\Users\\Salivs\\Data\\laragon\\www\\sigapp.dev\\app\\Libraries\\Refactor\\Exceptions\\SecurityException.php", "source_location": "L90"}]}