{"nodes": [{"id": "c_users_salivs_data_laragon_www_sigapp_dev_kiro_specs_list_kavling_redesign_issue_md", "label": "issue.md", "file_type": "document", "source_file": "C:\\Users\\Salivs\\Data\\laragon\\www\\sigapp.dev\\.kiro\\specs\\list-kavling-redesign\\issue.md", "source_location": "L1"}, {"id": "list_kavling_redesign_issue_redesain_halaman_list_kavling_global_datatables", "label": "Redesain Halaman List Kavling & Global DataTables", "file_type": "document", "source_file": "C:\\Users\\Salivs\\Data\\laragon\\www\\sigapp.dev\\.kiro\\specs\\list-kavling-redesign\\issue.md", "source_location": "L1"}, {"id": "list_kavling_redesign_issue_deskripsi_issue", "label": "Deskripsi Issue", "file_type": "document", "source_file": "C:\\Users\\Salivs\\Data\\laragon\\www\\sigapp.dev\\.kiro\\specs\\list-kavling-redesign\\issue.md", "source_location": "L3"}, {"id": "list_kavling_redesign_issue_detail_pekerjaan", "label": "Detail Pekerjaan", "file_type": "document", "source_file": "C:\\Users\\Salivs\\Data\\laragon\\www\\sigapp.dev\\.kiro\\specs\\list-kavling-redesign\\issue.md", "source_location": "L6"}, {"id": "list_kavling_redesign_issue_1_penerapan_gaya_global_untuk_datatables_compact_mode", "label": "1. Penerapan Gaya Global untuk DataTables (Compact Mode)", "file_type": "document", "source_file": "C:\\Users\\Salivs\\Data\\laragon\\www\\sigapp.dev\\.kiro\\specs\\list-kavling-redesign\\issue.md", "source_location": "L8"}, {"id": "list_kavling_redesign_issue_2_reposisi_kolom_aksi_di_list_kavling_php", "label": "2. Reposisi Kolom Aksi di `list-kavling.php`", "file_type": "document", "source_file": "C:\\Users\\Salivs\\Data\\laragon\\www\\sigapp.dev\\.kiro\\specs\\list-kavling-redesign\\issue.md", "source_location": "L16"}, {"id": "list_kavling_redesign_issue_3_integrasi_fungsi_edit_modal_siteplan", "label": "3. Integrasi Fungsi Edit & Modal Siteplan", "file_type": "document", "source_file": "C:\\Users\\Salivs\\Data\\laragon\\www\\sigapp.dev\\.kiro\\specs\\list-kavling-redesign\\issue.md", "source_location": "L21"}, {"id": "list_kavling_redesign_issue_referensi_requirements", "label": "Referensi Requirements", "file_type": "document", "source_file": "C:\\Users\\Salivs\\Data\\laragon\\www\\sigapp.dev\\.kiro\\specs\\list-kavling-redesign\\issue.md", "source_location": "L28"}], "edges": [{"source": "c_users_salivs_data_laragon_www_sigapp_dev_kiro_specs_list_kavling_redesign_issue_md", "target": "list_kavling_redesign_issue_redesain_halaman_list_kavling_global_datatables", "relation": "contains", "confidence": "EXTRACTED", "source_file": "C:\\Users\\Salivs\\Data\\laragon\\www\\sigapp.dev\\.kiro\\specs\\list-kavling-redesign\\issue.md", "source_location": "L1", "weight": 1.0}, {"source": "list_kavling_redesign_issue_redesain_halaman_list_kavling_global_datatables", "target": "list_kavling_redesign_issue_deskripsi_issue", "relation": "contains", "confidence": "EXTRACTED", "source_file": "C:\\Users\\Salivs\\Data\\laragon\\www\\sigapp.dev\\.kiro\\specs\\list-kavling-redesign\\issue.md", "source_location": "L3", "weight": 1.0}, {"source": "list_kavling_redesign_issue_deskripsi_issue", "target": "list_kavling_redesign_issue_detail_pekerjaan", "relation": "contains", "confidence": "EXTRACTED", "source_file": "C:\\Users\\Salivs\\Data\\laragon\\www\\sigapp.dev\\.kiro\\specs\\list-kavling-redesign\\issue.md", "source_location": "L6", "weight": 1.0}, {"source": "list_kavling_redesign_issue_detail_pekerjaan", "target": "list_kavling_redesign_issue_1_penerapan_gaya_global_untuk_datatables_compact_mode", "relation": "contains", "confidence": "EXTRACTED", "source_file": "C:\\Users\\Salivs\\Data\\laragon\\www\\sigapp.dev\\.kiro\\specs\\list-kavling-redesign\\issue.md", "source_location": "L8", "weight": 1.0}, {"source": "list_kavling_redesign_issue_detail_pekerjaan", "target": "list_kavling_redesign_issue_2_reposisi_kolom_aksi_di_list_kavling_php", "relation": "contains", "confidence": "EXTRACTED", "source_file": "C:\\Users\\Salivs\\Data\\laragon\\www\\sigapp.dev\\.kiro\\specs\\list-kavling-redesign\\issue.md", "source_location": "L16", "weight": 1.0}, {"source": "list_kavling_redesign_issue_detail_pekerjaan", "target": "list_kavling_redesign_issue_3_integrasi_fungsi_edit_modal_siteplan", "relation": "contains", "confidence": "EXTRACTED", "source_file": "C:\\Users\\Salivs\\Data\\laragon\\www\\sigapp.dev\\.kiro\\specs\\list-kavling-redesign\\issue.md", "source_location": "L21", "weight": 1.0}, {"source": "list_kavling_redesign_issue_redesain_halaman_list_kavling_global_datatables", "target": "list_kavling_redesign_issue_referensi_requirements", "relation": "contains", "confidence": "EXTRACTED", "source_file": "C:\\Users\\Salivs\\Data\\laragon\\www\\sigapp.dev\\.kiro\\specs\\list-kavling-redesign\\issue.md", "source_location": "L28", "weight": 1.0}], "input_tokens": 0, "output_tokens": 0}