{"nodes": [{"id": "c_users_salivs_data_laragon_www_sigapp_dev_app_commands_refactorscan_php", "label": "RefactorScan.php", "file_type": "code", "source_file": "C:\\Users\\Salivs\\Data\\laragon\\www\\sigapp.dev\\app\\Commands\\RefactorScan.php", "source_location": "L1"}, {"id": "commands_refactorscan_refactorscan", "label": "RefactorScan", "file_type": "code", "source_file": "C:\\Users\\Salivs\\Data\\laragon\\www\\sigapp.dev\\app\\Commands\\RefactorScan.php", "source_location": "L19"}, {"id": "commands_refactorscan_refactorscan_run", "label": ".run()", "file_type": "code", "source_file": "C:\\Users\\Salivs\\Data\\laragon\\www\\sigapp.dev\\app\\Commands\\RefactorScan.php", "source_location": "L58"}], "edges": [{"source": "c_users_salivs_data_laragon_www_sigapp_dev_app_commands_refactorscan_php", "target": "basecommand", "relation": "imports", "context": "import", "confidence": "EXTRACTED", "source_file": "C:\\Users\\Salivs\\Data\\laragon\\www\\sigapp.dev\\app\\Commands\\RefactorScan.php", "source_location": "L5", "weight": 1.0}, {"source": "c_users_salivs_data_laragon_www_sigapp_dev_app_commands_refactorscan_php", "target": "cli", "relation": "imports", "context": "import", "confidence": "EXTRACTED", "source_file": "C:\\Users\\Salivs\\Data\\laragon\\www\\sigapp.dev\\app\\Commands\\RefactorScan.php", "source_location": "L6", "weight": 1.0}, {"source": "c_users_salivs_data_laragon_www_sigapp_dev_app_commands_refactorscan_php", "target": "securityscanner", "relation": "imports", "context": "import", "confidence": "EXTRACTED", "source_file": "C:\\Users\\Salivs\\Data\\laragon\\www\\sigapp.dev\\app\\Commands\\RefactorScan.php", "source_location": "L7", "weight": 1.0}, {"source": "c_users_salivs_data_laragon_www_sigapp_dev_app_commands_refactorscan_php", "target": "moduleinventory", "relation": "imports", "context": "import", "confidence": "EXTRACTED", "source_file": "C:\\Users\\Salivs\\Data\\laragon\\www\\sigapp.dev\\app\\Commands\\RefactorScan.php", "source_location": "L8", "weight": 1.0}, {"source": "c_users_salivs_data_laragon_www_sigapp_dev_app_commands_refactorscan_php", "target": "securityreport", "relation": "imports", "context": "import", "confidence": "EXTRACTED", "source_file": "C:\\Users\\Salivs\\Data\\laragon\\www\\sigapp.dev\\app\\Commands\\RefactorScan.php", "source_location": "L9", "weight": 1.0}, {"source": "c_users_salivs_data_laragon_www_sigapp_dev_app_commands_refactorscan_php", "target": "commands_refactorscan_refactorscan", "relation": "contains", "confidence": "EXTRACTED", "source_file": "C:\\Users\\Salivs\\Data\\laragon\\www\\sigapp.dev\\app\\Commands\\RefactorScan.php", "source_location": "L19", "weight": 1.0}, {"source": "commands_refactorscan_refactorscan", "target": "commands_refactorscan_refactorscan_run", "relation": "method", "confidence": "EXTRACTED", "source_file": "C:\\Users\\Salivs\\Data\\laragon\\www\\sigapp.dev\\app\\Commands\\RefactorScan.php", "source_location": "L58", "weight": 1.0}], "raw_calls": [{"caller_nid": "commands_refactorscan_refactorscan_run", "callee": "CLI", "is_member_call": false, "source_file": "C:\\Users\\Salivs\\Data\\laragon\\www\\sigapp.dev\\app\\Commands\\RefactorScan.php", "source_location": "L60"}, {"caller_nid": "commands_refactorscan_refactorscan_run", "callee": "CLI", "is_member_call": false, "source_file": "C:\\Users\\Salivs\\Data\\laragon\\www\\sigapp.dev\\app\\Commands\\RefactorScan.php", "source_location": "L61"}, {"caller_nid": "commands_refactorscan_refactorscan_run", "callee": "file_exists", "is_member_call": false, "source_file": "C:\\Users\\Salivs\\Data\\laragon\\www\\sigapp.dev\\app\\Commands\\RefactorScan.php", "source_location": "L68"}, {"caller_nid": "commands_refactorscan_refactorscan_run", "callee": "CLI", "is_member_call": false, "source_file": "C:\\Users\\Salivs\\Data\\laragon\\www\\sigapp.dev\\app\\Commands\\RefactorScan.php", "source_location": "L69"}, {"caller_nid": "commands_refactorscan_refactorscan_run", "callee": "ModuleInventory", "is_member_call": false, "source_file": "C:\\Users\\Salivs\\Data\\laragon\\www\\sigapp.dev\\app\\Commands\\RefactorScan.php", "source_location": "L73"}, {"caller_nid": "commands_refactorscan_refactorscan_run", "callee": "file_get_contents", "is_member_call": false, "source_file": "C:\\Users\\Salivs\\Data\\laragon\\www\\sigapp.dev\\app\\Commands\\RefactorScan.php", "source_location": "L73"}, {"caller_nid": "commands_refactorscan_refactorscan_run", "callee": "array_shift", "is_member_call": false, "source_file": "C:\\Users\\Salivs\\Data\\laragon\\www\\sigapp.dev\\app\\Commands\\RefactorScan.php", "source_location": "L77"}, {"caller_nid": "commands_refactorscan_refactorscan_run", "callee": "getModule", "is_member_call": true, "source_file": "C:\\Users\\Salivs\\Data\\laragon\\www\\sigapp.dev\\app\\Commands\\RefactorScan.php", "source_location": "L81"}, {"caller_nid": "commands_refactorscan_refactorscan_run", "callee": "CLI", "is_member_call": false, "source_file": "C:\\Users\\Salivs\\Data\\laragon\\www\\sigapp.dev\\app\\Commands\\RefactorScan.php", "source_location": "L83"}, {"caller_nid": "commands_refactorscan_refactorscan_run", "callee": "CLI", "is_member_call": false, "source_file": "C:\\Users\\Salivs\\Data\\laragon\\www\\sigapp.dev\\app\\Commands\\RefactorScan.php", "source_location": "L87"}, {"caller_nid": "commands_refactorscan_refactorscan_run", "callee": "array_values", "is_member_call": false, "source_file": "C:\\Users\\Salivs\\Data\\laragon\\www\\sigapp.dev\\app\\Commands\\RefactorScan.php", "source_location": "L89"}, {"caller_nid": "commands_refactorscan_refactorscan_run", "callee": "CLI", "is_member_call": false, "source_file": "C:\\Users\\Salivs\\Data\\laragon\\www\\sigapp.dev\\app\\Commands\\RefactorScan.php", "source_location": "L90"}, {"caller_nid": "commands_refactorscan_refactorscan_run", "callee": "getModuleCount", "is_member_call": true, "source_file": "C:\\Users\\Salivs\\Data\\laragon\\www\\sigapp.dev\\app\\Commands\\RefactorScan.php", "source_location": "L90"}, {"caller_nid": "commands_refactorscan_refactorscan_run", "callee": "CLI", "is_member_call": false, "source_file": "C:\\Users\\Salivs\\Data\\laragon\\www\\sigapp.dev\\app\\Commands\\RefactorScan.php", "source_location": "L93"}, {"caller_nid": "commands_refactorscan_refactorscan_run", "callee": "is_dir", "is_member_call": false, "source_file": "C:\\Users\\Salivs\\Data\\laragon\\www\\sigapp.dev\\app\\Commands\\RefactorScan.php", "source_location": "L97"}, {"caller_nid": "commands_refactorscan_refactorscan_run", "callee": "mkdir", "is_member_call": false, "source_file": "C:\\Users\\Salivs\\Data\\laragon\\www\\sigapp.dev\\app\\Commands\\RefactorScan.php", "source_location": "L98"}, {"caller_nid": "commands_refactorscan_refactorscan_run", "callee": "scanModule", "is_member_call": true, "source_file": "C:\\Users\\Salivs\\Data\\laragon\\www\\sigapp.dev\\app\\Commands\\RefactorScan.php", "source_location": "L105"}, {"caller_nid": "commands_refactorscan_refactorscan_run", "callee": "getTotalCount", "is_member_call": true, "source_file": "C:\\Users\\Salivs\\Data\\laragon\\www\\sigapp.dev\\app\\Commands\\RefactorScan.php", "source_location": "L106"}, {"caller_nid": "commands_refactorscan_refactorscan_run", "callee": "getCriticalCount", "is_member_call": true, "source_file": "C:\\Users\\Salivs\\Data\\laragon\\www\\sigapp.dev\\app\\Commands\\RefactorScan.php", "source_location": "L108"}, {"caller_nid": "commands_refactorscan_refactorscan_run", "callee": "getHighCount", "is_member_call": true, "source_file": "C:\\Users\\Salivs\\Data\\laragon\\www\\sigapp.dev\\app\\Commands\\RefactorScan.php", "source_location": "L109"}, {"caller_nid": "commands_refactorscan_refactorscan_run", "callee": "getMediumCount", "is_member_call": true, "source_file": "C:\\Users\\Salivs\\Data\\laragon\\www\\sigapp.dev\\app\\Commands\\RefactorScan.php", "source_location": "L110"}, {"caller_nid": "commands_refactorscan_refactorscan_run", "callee": "getLowCount", "is_member_call": true, "source_file": "C:\\Users\\Salivs\\Data\\laragon\\www\\sigapp.dev\\app\\Commands\\RefactorScan.php", "source_location": "L111"}, {"caller_nid": "commands_refactorscan_refactorscan_run", "callee": "file_put_contents", "is_member_call": false, "source_file": "C:\\Users\\Salivs\\Data\\laragon\\www\\sigapp.dev\\app\\Commands\\RefactorScan.php", "source_location": "L115"}, {"caller_nid": "commands_refactorscan_refactorscan_run", "callee": "toJson", "is_member_call": true, "source_file": "C:\\Users\\Salivs\\Data\\laragon\\www\\sigapp.dev\\app\\Commands\\RefactorScan.php", "source_location": "L115"}, {"caller_nid": "commands_refactorscan_refactorscan_run", "callee": "getTotalCount", "is_member_call": true, "source_file": "C:\\Users\\Salivs\\Data\\laragon\\www\\sigapp.dev\\app\\Commands\\RefactorScan.php", "source_location": "L118"}, {"caller_nid": "commands_refactorscan_refactorscan_run", "callee": "CLI", "is_member_call": false, "source_file": "C:\\Users\\Salivs\\Data\\laragon\\www\\sigapp.dev\\app\\Commands\\RefactorScan.php", "source_location": "L119"}, {"caller_nid": "commands_refactorscan_refactorscan_run", "callee": "getTotalCount", "is_member_call": true, "source_file": "C:\\Users\\Salivs\\Data\\laragon\\www\\sigapp.dev\\app\\Commands\\RefactorScan.php", "source_location": "L119"}, {"caller_nid": "commands_refactorscan_refactorscan_run", "callee": "CLI", "is_member_call": false, "source_file": "C:\\Users\\Salivs\\Data\\laragon\\www\\sigapp.dev\\app\\Commands\\RefactorScan.php", "source_location": "L121"}, {"caller_nid": "commands_refactorscan_refactorscan_run", "callee": "CLI", "is_member_call": false, "source_file": "C:\\Users\\Salivs\\Data\\laragon\\www\\sigapp.dev\\app\\Commands\\RefactorScan.php", "source_location": "L125"}, {"caller_nid": "commands_refactorscan_refactorscan_run", "callee": "CLI", "is_member_call": false, "source_file": "C:\\Users\\Salivs\\Data\\laragon\\www\\sigapp.dev\\app\\Commands\\RefactorScan.php", "source_location": "L128"}, {"caller_nid": "commands_refactorscan_refactorscan_run", "callee": "CLI", "is_member_call": false, "source_file": "C:\\Users\\Salivs\\Data\\laragon\\www\\sigapp.dev\\app\\Commands\\RefactorScan.php", "source_location": "L129"}, {"caller_nid": "commands_refactorscan_refactorscan_run", "callee": "CLI", "is_member_call": false, "source_file": "C:\\Users\\Salivs\\Data\\laragon\\www\\sigapp.dev\\app\\Commands\\RefactorScan.php", "source_location": "L130"}, {"caller_nid": "commands_refactorscan_refactorscan_run", "callee": "CLI", "is_member_call": false, "source_file": "C:\\Users\\Salivs\\Data\\laragon\\www\\sigapp.dev\\app\\Commands\\RefactorScan.php", "source_location": "L133"}, {"caller_nid": "commands_refactorscan_refactorscan_run", "callee": "CLI", "is_member_call": false, "source_file": "C:\\Users\\Salivs\\Data\\laragon\\www\\sigapp.dev\\app\\Commands\\RefactorScan.php", "source_location": "L135"}, {"caller_nid": "commands_refactorscan_refactorscan_run", "callee": "CLI", "is_member_call": false, "source_file": "C:\\Users\\Salivs\\Data\\laragon\\www\\sigapp.dev\\app\\Commands\\RefactorScan.php", "source_location": "L139"}, {"caller_nid": "commands_refactorscan_refactorscan_run", "callee": "CLI", "is_member_call": false, "source_file": "C:\\Users\\Salivs\\Data\\laragon\\www\\sigapp.dev\\app\\Commands\\RefactorScan.php", "source_location": "L141"}, {"caller_nid": "commands_refactorscan_refactorscan_run", "callee": "CLI", "is_member_call": false, "source_file": "C:\\Users\\Salivs\\Data\\laragon\\www\\sigapp.dev\\app\\Commands\\RefactorScan.php", "source_location": "L145"}, {"caller_nid": "commands_refactorscan_refactorscan_run", "callee": "CLI", "is_member_call": false, "source_file": "C:\\Users\\Salivs\\Data\\laragon\\www\\sigapp.dev\\app\\Commands\\RefactorScan.php", "source_location": "L147"}, {"caller_nid": "commands_refactorscan_refactorscan_run", "callee": "CLI", "is_member_call": false, "source_file": "C:\\Users\\Salivs\\Data\\laragon\\www\\sigapp.dev\\app\\Commands\\RefactorScan.php", "source_location": "L150"}, {"caller_nid": "commands_refactorscan_refactorscan_run", "callee": "CLI", "is_member_call": false, "source_file": "C:\\Users\\Salivs\\Data\\laragon\\www\\sigapp.dev\\app\\Commands\\RefactorScan.php", "source_location": "L151"}, {"caller_nid": "commands_refactorscan_refactorscan_run", "callee": "CLI", "is_member_call": false, "source_file": "C:\\Users\\Salivs\\Data\\laragon\\www\\sigapp.dev\\app\\Commands\\RefactorScan.php", "source_location": "L152"}, {"caller_nid": "commands_refactorscan_refactorscan_run", "callee": "CLI", "is_member_call": false, "source_file": "C:\\Users\\Salivs\\Data\\laragon\\www\\sigapp.dev\\app\\Commands\\RefactorScan.php", "source_location": "L153"}, {"caller_nid": "commands_refactorscan_refactorscan_run", "callee": "CLI", "is_member_call": false, "source_file": "C:\\Users\\Salivs\\Data\\laragon\\www\\sigapp.dev\\app\\Commands\\RefactorScan.php", "source_location": "L155"}, {"caller_nid": "commands_refactorscan_refactorscan_run", "callee": "CLI", "is_member_call": false, "source_file": "C:\\Users\\Salivs\\Data\\laragon\\www\\sigapp.dev\\app\\Commands\\RefactorScan.php", "source_location": "L158"}, {"caller_nid": "commands_refactorscan_refactorscan_run", "callee": "getMessage", "is_member_call": true, "source_file": "C:\\Users\\Salivs\\Data\\laragon\\www\\sigapp.dev\\app\\Commands\\RefactorScan.php", "source_location": "L158"}]}